blobtoolkit_host.py
lib/__init__.py
lib/host.py
lib/version.py
blobtoolkit_host-4.5.0.dist-info/METADATA
blobtoolkit_host-4.5.0.dist-info/WHEEL
blobtoolkit_host-4.5.0.dist-info/entry_points.txt
blobtoolkit_host-4.5.0.dist-info/top_level.txt
blobtoolkit_host-4.5.0.dist-info/RECORD
